phrasplit/__init__.py
phrasplit/_version.py
phrasplit/abbreviations.py
phrasplit/cli.py
phrasplit/py.typed
phrasplit/splitter.py
phrasplit/splitter_without_spacy.py
phrasplit/types.py
phrasplit/utils.py
phrasplit-0.3.2.dist-info/licenses/LICENSE
phrasplit-0.3.2.dist-info/METADATA
phrasplit-0.3.2.dist-info/WHEEL
phrasplit-0.3.2.dist-info/entry_points.txt
phrasplit-0.3.2.dist-info/top_level.txt
phrasplit-0.3.2.dist-info/RECORD
